lapjv.cp310-win_amd64.pyd
lapjv_numpy2-1.3.26.dist-info/LICENSE
lapjv_numpy2-1.3.26.dist-info/METADATA
lapjv_numpy2-1.3.26.dist-info/WHEEL
lapjv_numpy2-1.3.26.dist-info/top_level.txt
lapjv_numpy2-1.3.26.dist-info/RECORD
